odoo/addons/base_future_response/README.rst
odoo/addons/base_future_response/__init__.py
odoo/addons/base_future_response/__manifest__.py
odoo/addons/base_future_response/future_response.py
odoo/addons/base_future_response/i18n/base_future_response.pot
odoo/addons/base_future_response/readme/DESCRIPTION.rst
odoo/addons/base_future_response/readme/ROADMAP.rst
odoo/addons/base_future_response/static/description/icon.png
odoo/addons/base_future_response/static/description/index.html
odoo/addons/base_future_response/tests/__init__.py
odoo/addons/base_future_response/tests/test_future_response.py
odoo14_addon_base_future_response-14.0.1.0.2.dist-info/METADATA
odoo14_addon_base_future_response-14.0.1.0.2.dist-info/WHEEL
odoo14_addon_base_future_response-14.0.1.0.2.dist-info/top_level.txt
odoo14_addon_base_future_response-14.0.1.0.2.dist-info/RECORD
